TerraLib/BaseConversion.py
TerraLib/Excel.py
TerraLib/Git.py
TerraLib/SubProcess.py
TerraLib/Svn.py
TerraLib/Time.py
TerraLib/__init__.py
terralib-1.1.4.dist-info/licenses/LICENSE.md
terralib-1.1.4.dist-info/METADATA
terralib-1.1.4.dist-info/WHEEL
terralib-1.1.4.dist-info/top_level.txt
terralib-1.1.4.dist-info/RECORD
