Metadata-Version: 2.4
Name: TerraLib
Version: 1.1.4
Summary: Common libs for use, include operation on excel, print and so on.
Author-email: TerraJuly <caijie_hui@163.com>
Maintainer-email: TerraJuly <caijie_hui@163.com>
License: MIT License
Project-URL: Homepage, https://github.com/TerraJuly/TerraLib
Classifier: Development Status :: 3 - Alpha
Classifier: Intended Audience :: Developers
Classifier: Topic :: Software Development :: Build Tools
Classifier: License :: OSI Approved :: MIT License
Classifier: Programming Language :: Python :: 3
Classifier: Programming Language :: Python :: 3.6
Classifier: Programming Language :: Python :: 3.7
Classifier: Programming Language :: Python :: 3.8
Classifier: Programming Language :: Python :: 3.9
Classifier: Programming Language :: Python :: 3.10
Classifier: Programming Language :: Python :: 3.11
Classifier: Programming Language :: Python :: 3.12
License-File: LICENSE.md
Requires-Dist: xlrd==1.2.0
Requires-Dist: openpyxl>=3.0.0
Dynamic: license-file
